[ {
  "code" : "2081",
  "name" : "Геозавод",
  "schedule" : [ "07:10", "08:50", "11:55", "13:35", "15:15", "17:40", "19:20" ]
}, {
  "code" : "225",
  "name" : "Площадь XX партсъезда",
  "schedule" : [ "05:40", "07:11", "08:51", "11:56", "13:36", "15:16", "17:41", "19:21" ]
}, {
  "code" : "316",
  "name" : "ул. Березниковская",
  "schedule" : [ "05:42", "07:13", "08:53", "11:58", "13:38", "15:18", "17:43", "19:23" ]
}, {
  "code" : "286",
  "name" : "Сады",
  "schedule" : [ "05:45", "07:16", "08:56", "12:01", "13:41", "15:21", "17:46", "19:26" ]
}, {
  "code" : "296",
  "name" : "ТЭЦ-4",
  "schedule" : [ "05:46", "07:17", "08:57", "12:02", "13:42", "15:22", "17:47", "19:27" ]
}, {
  "code" : "299",
  "name" : "ТЦ Макси",
  "schedule" : [ "05:47", "07:18", "08:58", "12:03", "13:43", "15:23", "17:48", "19:28" ]
}, {
  "code" : "260",
  "name" : "ул. Луганская",
  "schedule" : [ "05:48", "07:19", "08:59", "12:04", "13:44", "15:24", "17:49", "19:29" ]
}, {
  "code" : "258",
  "name" : "Авторынок",
  "schedule" : [ "05:49", "07:20", "09:00", "12:05", "13:45", "15:25", "17:50", "19:30" ]
}, {
  "code" : "649",
  "name" : "ул. Кольцова",
  "schedule" : [ "05:50", "07:21", "09:01", "12:06", "13:46", "15:26", "17:51", "19:31" ]
}, {
  "code" : "647",
  "name" : "ул. Циолковского",
  "schedule" : [ "05:52", "07:23", "09:03", "12:08", "13:48", "15:28", "17:53", "19:33" ]
}, {
  "code" : "45",
  "name" : "Мечта",
  "schedule" : [ "05:53", "07:24", "09:04", "12:09", "13:49", "15:29", "17:54", "19:34" ]
}, {
  "code" : "605",
  "name" : "Перинатальный центр",
  "schedule" : [ "05:55", "07:26", "09:06", "12:11", "13:51", "15:31", "17:56", "19:36" ]
}, {
  "code" : "75",
  "name" : "ул. Московская",
  "schedule" : [ "05:58", "07:29", "09:09", "12:14", "13:54", "15:34", "17:59", "19:39" ]
}, {
  "code" : "903",
  "name" : "Проспект Строителей",
  "schedule" : [ "05:59", "07:30", "09:10", "12:15", "13:55", "15:35", "18:00", "19:40" ]
}, {
  "code" : "104",
  "name" : "Общежитие",
  "schedule" : [ "06:00", "07:31", "09:11", "12:16", "13:56", "15:36", "18:01", "19:41" ]
}, {
  "code" : "12",
  "name" : "Магазин \"Атлант\"",
  "schedule" : [ "06:03", "07:34", "09:14", "12:19", "13:59", "15:39", "18:04", "19:44" ]
}, {
  "code" : "107",
  "name" : "Площадь Маршала Конева",
  "schedule" : [ "06:05", "07:36", "09:16", "12:21", "14:01", "15:41", "18:06", "19:46" ]
}, {
  "code" : "109",
  "name" : "Храм целителя Пантелеимона",
  "schedule" : [ "06:06", "07:37", "09:17", "12:22", "14:02", "15:42", "18:07", "19:47" ]
}, {
  "code" : "411",
  "name" : "ул. Воровского",
  "schedule" : [ "06:07", "07:38", "09:18", "12:23", "14:03", "15:43", "18:08", "19:48" ]
}, {
  "code" : "412",
  "name" : "ул. Солнечная",
  "schedule" : [ "06:08", "07:39", "09:19", "12:24", "14:04", "15:44", "18:09", "19:49" ]
}, {
  "code" : "413",
  "name" : "Веста",
  "schedule" : [ "06:10", "07:41", "09:21", "12:26", "14:06", "15:46", "18:11", "19:51" ]
}, {
  "code" : "414",
  "name" : "База \"Производственная\"",
  "schedule" : [ "06:12", "07:44", "09:24", "12:29", "14:09", "15:49", "18:14", "19:54" ]
}, {
  "code" : "300",
  "name" : "Дом техники",
  "schedule" : [ "06:14", "07:46", "09:26", "12:31", "14:11", "15:51", "18:16", "19:56" ]
}, {
  "code" : "304",
  "name" : "Солнечный проезд",
  "schedule" : [ "06:15", "07:47", "09:27", "12:32", "14:12", "15:52", "18:17", "19:57" ]
}, {
  "code" : "306",
  "name" : "Завод \"Сельмаш\"",
  "schedule" : [ "06:15", "07:47", "09:27", "12:32", "14:12", "15:52", "18:17", "19:57" ]
}, {
  "code" : "329",
  "name" : "ул. Ульяновская",
  "schedule" : [ "06:17", "07:49", "09:29", "12:34", "14:14", "15:54", "18:19", "19:59" ]
}, {
  "code" : "126",
  "name" : "Европейские улочки",
  "schedule" : [ "06:18", "07:50", "09:30", "12:35", "14:15", "15:55", "18:20", "20:00" ]
}, {
  "code" : "1320",
  "name" : "ул. Анжелия Михеева",
  "schedule" : [ "06:19", "07:51", "09:31", "12:36", "14:16", "15:56", "18:21", "20:01" ]
}, {
  "code" : "1321",
  "name" : "Школа №26",
  "schedule" : [ "06:20", "07:52", "09:32", "12:37", "14:17", "15:57", "18:22", "20:02" ]
}, {
  "code" : "1397",
  "name" : "ЖК \"Знак\"",
  "schedule" : [ "06:24", "07:59", "09:39", "12:44", "14:24", "16:04", "18:29", "20:09" ]
}, {
  "code" : "217",
  "name" : "ул. Капитана Дорофеева",
  "schedule" : [ "06:26", "08:01", "09:41", "12:46", "14:26", "16:06", "18:31", "20:11" ]
}, {
  "code" : "1322",
  "name" : "Школа №26",
  "schedule" : [ "06:26", "08:01", "09:41", "12:46", "14:26", "16:06", "18:31", "20:11" ]
}, {
  "code" : "1319",
  "name" : "ул. Анжелия Михеева",
  "schedule" : [ "06:27", "08:02", "09:42", "12:47", "14:27", "16:07", "18:32", "20:12" ]
}, {
  "code" : "125",
  "name" : "Европейские улочки",
  "schedule" : [ "06:29", "08:04", "09:44", "12:49", "14:29", "16:09", "18:34", "20:14" ]
}, {
  "code" : "330",
  "name" : "ул. Ульяновская",
  "schedule" : [ "06:31", "08:06", "09:46", "12:51", "14:31", "16:11", "18:36", "20:16" ]
}, {
  "code" : "307",
  "name" : "Завод \"Сельмаш\"",
  "schedule" : [ "06:34", "08:09", "09:49", "12:54", "14:34", "16:14", "18:39", "20:19" ]
}, {
  "code" : "303",
  "name" : "Клиника медицинского университета",
  "schedule" : [ "06:37", "08:12", "09:52", "12:57", "14:37", "16:17", "18:42", "20:22" ]
}, {
  "code" : "425",
  "name" : "ул. Щорса",
  "schedule" : [ "06:39", "08:15", "09:55", "13:00", "14:40", "16:20", "18:45", "20:25" ]
}, {
  "code" : "426",
  "name" : "База \"Производственная\"",
  "schedule" : [ "06:41", "08:17", "09:57", "13:02", "14:42", "16:22", "18:47", "20:27" ]
}, {
  "code" : "427",
  "name" : "Веста",
  "schedule" : [ "06:44", "08:20", "10:00", "13:05", "14:45", "16:25", "18:50", "20:30" ]
}, {
  "code" : "428",
  "name" : "ул. Солнечная",
  "schedule" : [ "06:48", "08:24", "10:04", "13:09", "14:49", "16:29", "18:54", "20:34" ]
}, {
  "code" : "429",
  "name" : "ул. Воровского",
  "schedule" : [ "06:51", "08:27", "10:07", "13:12", "14:52", "16:32", "18:57", "20:37" ]
}, {
  "code" : "430",
  "name" : "ул. Производственная",
  "schedule" : [ "06:52", "08:28", "10:08", "13:13", "14:53", "16:33", "18:58", "20:38" ]
}, {
  "code" : "265",
  "name" : "Мечта",
  "schedule" : [ "06:55", "08:31", "10:11", "13:16", "14:56", "16:36", "19:01", "20:41" ]
}, {
  "code" : "267",
  "name" : "ул. Циолковского",
  "schedule" : [ "06:56", "08:32", "10:12", "13:17", "14:57", "16:37", "19:02", "20:42" ]
}, {
  "code" : "268",
  "name" : "ул. Кольцова",
  "schedule" : [ "06:57", "08:33", "10:13", "13:18", "14:58", "16:38", "19:03", "20:43" ]
}, {
  "code" : "269",
  "name" : "Авторынок",
  "schedule" : [ "06:58", "08:34", "10:14", "13:19", "14:59", "16:39", "19:04", "20:44" ]
}, {
  "code" : "275",
  "name" : "ул. Луганская",
  "schedule" : [ "06:59", "08:36", "10:16", "13:21", "15:01", "16:41", "19:06", "20:46" ]
}, {
  "code" : "311",
  "name" : "ТЦ Макси",
  "schedule" : [ "07:01", "08:37", "10:17", "13:22", "15:02", "16:42", "19:07", "20:47" ]
}, {
  "code" : "313",
  "name" : "ТЭЦ-4",
  "schedule" : [ "07:02", "08:38", "10:18", "13:23", "15:03", "16:43", "19:08", "20:48" ]
}, {
  "code" : "315",
  "name" : "Сады",
  "schedule" : [ "07:03", "08:40", "10:20", "13:25", "15:05", "16:45", "19:10", "20:50" ]
}, {
  "code" : "279",
  "name" : "ул. Березниковская",
  "schedule" : [ "07:05", "08:42", "10:22", "13:27", "15:07", "16:47", "19:12", "20:52" ]
}, {
  "code" : "205",
  "name" : "Площадь XX партсъезда",
  "schedule" : [ "07:07", "08:44", "10:24", "13:29", "15:09", "16:49", "19:14", "20:54" ]
}, {
  "code" : "2081",
  "name" : "Геозавод",
  "schedule" : [ "07:10", "08:50", "11:55", "13:35", "15:15", "17:40", "19:20" ]
}, {
  "code" : "652",
  "name" : "Школа искусств \"Рапсодия\"",
  "schedule" : [ ]
}, {
  "code" : "651",
  "name" : "Западные бани",
  "schedule" : [ ]
}, {
  "code" : "653",
  "name" : "Школа №42",
  "schedule" : [ ]
}, {
  "code" : "41",
  "name" : "Красная горка",
  "schedule" : [ ]
}, {
  "code" : "43",
  "name" : "Красная горка",
  "schedule" : [ ]
}, {
  "code" : "804",
  "name" : "ул. Андрея Упита",
  "schedule" : [ ]
}, {
  "code" : "648",
  "name" : "Школа №42",
  "schedule" : [ ]
}, {
  "code" : "650",
  "name" : "Западные Бани",
  "schedule" : [ ]
} ]